sft_data_generator/__init__.py
sft_data_generator/main.py
sft_data_generator-0.0.3.dist-info/LICENSE
sft_data_generator-0.0.3.dist-info/METADATA
sft_data_generator-0.0.3.dist-info/WHEEL
sft_data_generator-0.0.3.dist-info/entry_points.txt
sft_data_generator-0.0.3.dist-info/top_level.txt
sft_data_generator-0.0.3.dist-info/RECORD
