Metadata-Version: 2.1
Name: sft-data-generator
Version: 0.0.3
Summary: A tool for generating data for SFT using LLM
Home-page: https://github.com/Treedy2020/sft_data_generator
Author: Richard_Cui
Author-email: treedy2020@icloud.com
Classifier: Programming Language :: Python :: 3
Classifier: License :: OSI Approved :: MIT License
Classifier: Operating System :: OS Independent
Requires-Python: >=3.8
License-File: LICENSE
Requires-Dist: openai ~=1.13.3
Requires-Dist: pandas ~=2.2.1
Requires-Dist: jsonlines ~=4.0.0
Requires-Dist: tqdm ~=4.66.2
Requires-Dist: setuptools ~=68.2.2
Requires-Dist: openpyxl ~=3.1.2
